CHANGES.txt
bootstrap.py
buildout.cfg
setup.py
src/z3c/__init__.py
src/z3c.multifieldindex.egg-info/PKG-INFO
src/z3c.multifieldindex.egg-info/SOURCES.txt
src/z3c.multifieldindex.egg-info/dependency_links.txt
src/z3c.multifieldindex.egg-info/namespace_packages.txt
src/z3c.multifieldindex.egg-info/not-zip-safe
src/z3c.multifieldindex.egg-info/requires.txt
src/z3c.multifieldindex.egg-info/top_level.txt
src/z3c/multifieldindex/README.txt
src/z3c/multifieldindex/__init__.py
src/z3c/multifieldindex/configure.zcml
src/z3c/multifieldindex/index.py
src/z3c/multifieldindex/interfaces.py
src/z3c/multifieldindex/subindex.py
src/z3c/multifieldindex/tests.py