Metadata-Version: 1.0
Name: z3c.multifieldindex
Version: 3.4.0
Summary: Multi-field index for zope catalog
Home-page: http://pypi.python.org/pypi/z3c.multifieldindex
Author: Dan Korostelev and Zope Community
Author-email: zope-dev@zope.org
License: ZPL 2.1
Platform: UNKNOWN
